ccui_web/__init__.py
ccui_web/app.py
ccui_web/templates/edit.html
ccui_web/templates/edit_mcp.html
ccui_web/templates/index.html
ccui_web-0.1.2.dist-info/METADATA
ccui_web-0.1.2.dist-info/WHEEL
ccui_web-0.1.2.dist-info/entry_points.txt
ccui_web-0.1.2.dist-info/top_level.txt
ccui_web-0.1.2.dist-info/RECORD
