Metadata-Version: 2.4
Name: ccui-web
Version: 0.1.2
Summary: Web UI for managing Claude Code env and MCP configs
Author: Your Name
Project-URL: Homepage, https://github.com/your-org/your-repo
Requires-Python: >=3.9
Requires-Dist: Flask==3.0.3
Requires-Dist: Flask-SQLAlchemy==3.1.1
Requires-Dist: SQLAlchemy==2.0.30
